[
  {
    "display_norm": "huber, ferdinand ludwig",
    "composite_id": [
      "musik_90_4_11"
    ],
    "family_name": "Huber",
    "given_names": "Ferdinand Ludwig",
    "name_prefix": null,
    "name_particles": null,
    "name_suffix": null,
    "single_name": null,
    "is_organisation": false,
    "match_found": false,
    "matched_unified_id": null,
    "matched_person_id": null,
    "unified_id": "huber_ferdinand_l",
    "_source_custom_id": "batch_nopes_016"
  },
  {
    "display_norm": "huber, martin",
    "composite_id": [
      "erstausgaben_238_10_78",
      "erstausgaben_226_10_78"
    ],
    "family_name": "Huber",
    "given_names": "Martin",
    "name_prefix": null,
    "name_particles": null,
    "name_suffix": null,
    "single_name": null,
    "is_organisation": false,
    "match_found": false,
    "matched_unified_id": null,
    "matched_person_id": null,
    "unified_id": "huber_martin",
    "_source_custom_id": "batch_nopes_016"
  },
  {
    "display_norm": "humboldt, a. v.",
    "composite_id": [
      "reisen_258_11_13"
    ],
    "family_name": "Humboldt",
    "given_names": "A.",
    "name_prefix": null,
    "name_particles": "von",
    "name_suffix": null,
    "single_name": null,
    "is_organisation": false,
    "match_found": true,
    "matched_unified_id": "humboldt_alexander_von",
    "matched_person_id": 3088,
    "unified_id": null,
    "_source_custom_id": "batch_nopes_016"
  },
  {
    "display_norm": "hurm, otto",
    "composite_id": [
      "erstausgaben_1440_58_78"
    ],
    "family_name": "Hurm",
    "given_names": "Otto",
    "name_prefix": null,
    "name_particles": null,
    "name_suffix": null,
    "single_name": null,
    "is_organisation": false,
    "match_found": false,
    "matched_unified_id": null,
    "matched_person_id": null,
    "unified_id": "hurm_otto",
    "_source_custom_id": "batch_nopes_016"
  },
  {
    "display_norm": "husslein-arco, agnes",
    "composite_id": [
      "kunstbuecher_524_21_38"
    ],
    "family_name": "Husslein-Arco",
    "given_names": "Agnes",
    "name_prefix": null,
    "name_particles": null,
    "name_suffix": null,
    "single_name": null,
    "is_organisation": false,
    "match_found": false,
    "matched_unified_id": null,
    "matched_person_id": null,
    "unified_id": "husslein-arco_agnes",
    "_source_custom_id": "batch_nopes_016"
  },
  {
    "display_norm": "hutter, heribert",
    "composite_id": [
      "kunstbuecher_188_8_38"
    ],
    "family_name": "Hutter",
    "given_names": "Heribert",
    "name_prefix": null,
    "name_particles": null,
    "name_suffix": null,
    "single_name": null,
    "is_organisation": false,
    "match_found": false,
    "matched_unified_id": null,
    "matched_person_id": null,
    "unified_id": "hutter_heribert",
    "_source_custom_id": "batch_nopes_016"
  },
  {
    "display_norm": "hutter, wolfgang",
    "composite_id": [
      "kunstbuecher_240_10_38"
    ],
    "family_name": "Hutter",
    "given_names": "Wolfgang",
    "name_prefix": null,
    "name_particles": null,
    "name_suffix": null,
    "single_name": null,
    "is_organisation": false,
    "match_found": false,
    "matched_unified_id": null,
    "matched_person_id": null,
    "unified_id": "hutter_wolfgang",
    "_source_custom_id": "batch_nopes_016"
  },
  {
    "display_norm": "höch, hannah",
    "composite_id": [
      "kunstbuecher_209_9_38"
    ],
    "family_name": "Höch",
    "given_names": "Hannah",
    "name_prefix": null,
    "name_particles": null,
    "name_suffix": null,
    "single_name": null,
    "is_organisation": false,
    "match_found": false,
    "matched_unified_id": null,
    "matched_person_id": null,
    "unified_id": "hoch_hannah",
    "_source_custom_id": "batch_nopes_016"
  },
  {
    "display_norm": "höhne, horst",
    "composite_id": [
      "briefe_336_14_15"
    ],
    "family_name": "Höhne",
    "given_names": "Horst",
    "name_prefix": null,
    "name_particles": null,
    "name_suffix": null,
    "single_name": null,
    "is_organisation": false,
    "match_found": false,
    "matched_unified_id": null,
    "matched_person_id": null,
    "unified_id": "hohne_horst",
    "_source_custom_id": "batch_nopes_016"
  },
  {
    "display_norm": "hölbling, lothar",
    "composite_id": [
      "wien_51_3_10"
    ],
    "family_name": "Hölbling",
    "given_names": "Lothar",
    "name_prefix": null,
    "name_particles": null,
    "name_suffix": null,
    "single_name": null,
    "is_organisation": false,
    "match_found": false,
    "matched_unified_id": null,
    "matched_person_id": null,
    "unified_id": "holbling_lothar",
    "_source_custom_id": "batch_nopes_016"
  },
  {
    "display_norm": "hölter, achim",
    "composite_id": [
      "monographien_55_3_3"
    ],
    "family_name": "Hölter",
    "given_names": "Achim",
    "name_prefix": null,
    "name_particles": null,
    "name_suffix": null,
    "single_name": null,
    "is_organisation": false,
    "match_found": false,
    "matched_unified_id": null,
    "matched_person_id": null,
    "unified_id": "holter_achim",
    "_source_custom_id": "batch_nopes_016"
  },
  {
    "display_norm": "hörisch, jochen",
    "composite_id": [
      "literatur_141_6_12",
      "de-lit-texte_8_1_20"
    ],
    "family_name": "Hörisch",
    "given_names": "Jochen",
    "name_prefix": null,
    "name_particles": null,
    "name_suffix": null,
    "single_name": null,
    "is_organisation": false,
    "match_found": false,
    "matched_unified_id": null,
    "matched_person_id": null,
    "unified_id": "horisch_jochen",
    "_source_custom_id": "batch_nopes_016"
  },
  {
    "display_norm": "hörmann, werner",
    "composite_id": [
      "okkultismus_41_2_8"
    ],
    "family_name": "Hörmann",
    "given_names": "Werner",
    "name_prefix": null,
    "name_particles": null,
    "name_suffix": null,
    "single_name": null,
    "is_organisation": false,
    "match_found": false,
    "matched_unified_id": null,
    "matched_person_id": null,
    "unified_id": "hormann_werner",
    "_source_custom_id": "batch_nopes_016"
  },
  {
    "display_norm": "hüttenegger, bernhard",
    "composite_id": [
      "signierte_94_4_10"
    ],
    "family_name": "Hüttenegger",
    "given_names": "Bernhard",
    "name_prefix": null,
    "name_particles": null,
    "name_suffix": null,
    "single_name": null,
    "is_organisation": false,
    "match_found": false,
    "matched_unified_id": null,
    "matched_person_id": null,
    "unified_id": "huttenegger_bernhard",
    "_source_custom_id": "batch_nopes_016"
  },
  {
    "display_norm": "ib, giovanni di boccaccio",
    "composite_id": [
      "insel_297_12_27"
    ],
    "family_name": null,
    "given_names": null,
    "name_prefix": null,
    "name_particles": null,
    "name_suffix": null,
    "single_name": "Giovanni di Boccaccio",
    "is_organisation": false,
    "match_found": false,
    "matched_unified_id": null,
    "matched_person_id": null,
    "unified_id": "giovanni_di_boccaccio",
    "_source_custom_id": "batch_nopes_016"
  },
  {
    "display_norm": "ib, paul hindemith",
    "composite_id": [
      "insel_523_21_27"
    ],
    "family_name": "Hindemith",
    "given_names": "Paul",
    "name_prefix": null,
    "name_particles": null,
    "name_suffix": null,
    "single_name": null,
    "is_organisation": false,
    "match_found": false,
    "matched_unified_id": null,
    "matched_person_id": null,
    "unified_id": "hindemith_paul",
    "_source_custom_id": "batch_nopes_016"
  },
  {
    "display_norm": "ifflandt, august",
    "composite_id": [
      "musik_90_4_11"
    ],
    "family_name": "Ifflandt",
    "given_names": "August",
    "name_prefix": null,
    "name_particles": null,
    "name_suffix": null,
    "single_name": null,
    "is_organisation": false,
    "match_found": false,
    "matched_unified_id": null,
    "matched_person_id": null,
    "unified_id": "ifflandt_august",
    "_source_custom_id": "batch_nopes_016"
  },
  {
    "display_norm": "ifrah, georges",
    "composite_id": [
      "sonstiges_19_1_4"
    ],
    "family_name": "Ifrah",
    "given_names": "Georges",
    "name_prefix": null,
    "name_particles": null,
    "name_suffix": null,
    "single_name": null,
    "is_organisation": false,
    "match_found": false,
    "matched_unified_id": null,
    "matched_person_id": null,
    "unified_id": "ifrah_georges",
    "_source_custom_id": "batch_nopes_016"
  },
  {
    "display_norm": "ingeborg",
    "composite_id": [
      "russland_283_12_17"
    ],
    "family_name": null,
    "given_names": null,
    "name_prefix": null,
    "name_particles": null,
    "name_suffix": null,
    "single_name": "Ingeborg",
    "is_organisation": false,
    "match_found": false,
    "matched_unified_id": null,
    "matched_person_id": null,
    "unified_id": "ingeborg",
    "_source_custom_id": "batch_nopes_016"
  },
  {
    "display_norm": "ingrisch, lotte",
    "composite_id": [
      "oesterreich_72_3_13"
    ],
    "family_name": "Ingrisch",
    "given_names": "Lotte",
    "name_prefix": null,
    "name_particles": null,
    "name_suffix": null,
    "single_name": null,
    "is_organisation": false,
    "match_found": false,
    "matched_unified_id": null,
    "matched_person_id": null,
    "unified_id": "ingrisch_lotte",
    "_source_custom_id": "batch_nopes_016"
  },
  {
    "display_norm": "innerhofer, roland",
    "composite_id": [
      "oesterreich_215_9_13"
    ],
    "family_name": "Innerhofer",
    "given_names": "Roland",
    "name_prefix": null,
    "name_particles": null,
    "name_suffix": null,
    "single_name": null,
    "is_organisation": false,
    "match_found": false,
    "matched_unified_id": null,
    "matched_person_id": null,
    "unified_id": "innerhofer_roland",
    "_source_custom_id": "batch_nopes_016"
  },
  {
    "display_norm": "internationale stiftung mozarteum salzburg",
    "composite_id": [
      "musik_82_4_11"
    ],
    "family_name": null,
    "given_names": null,
    "name_prefix": null,
    "name_particles": null,
    "name_suffix": null,
    "single_name": "Internationale Stiftung Mozarteum Salzburg",
    "is_organisation": true,
    "match_found": false,
    "matched_unified_id": null,
    "matched_person_id": null,
    "unified_id": "internationale_stiftung_mozarteum_salzburg",
    "_source_custom_id": "batch_nopes_016"
  },
  {
    "display_norm": "isaacs, reginald r.",
    "composite_id": [
      "biographie_301_13_27"
    ],
    "family_name": "Isaacs",
    "given_names": "Reginald R.",
    "name_prefix": null,
    "name_particles": null,
    "name_suffix": null,
    "single_name": null,
    "is_organisation": false,
    "match_found": false,
    "matched_unified_id": null,
    "matched_person_id": null,
    "unified_id": "isaacs_reginald_r",
    "_source_custom_id": "batch_nopes_016"
  },
  {
    "display_norm": "ivanka, endre von",
    "composite_id": [
      "mittelalter_57_3_7"
    ],
    "family_name": "Ivanka",
    "given_names": "Endre",
    "name_prefix": null,
    "name_particles": "von",
    "name_suffix": null,
    "single_name": null,
    "is_organisation": false,
    "match_found": false,
    "matched_unified_id": null,
    "matched_person_id": null,
    "unified_id": "ivanka_endre",
    "_source_custom_id": "batch_nopes_016"
  },
  {
    "display_norm": "jacobi, renate",
    "composite_id": [
      "islam_12_1_3"
    ],
    "family_name": "Jacobi",
    "given_names": "Renate",
    "name_prefix": null,
    "name_particles": null,
    "name_suffix": null,
    "single_name": null,
    "is_organisation": false,
    "match_found": false,
    "matched_unified_id": null,
    "matched_person_id": null,
    "unified_id": "jacobi_renate",
    "_source_custom_id": "batch_nopes_016"
  },
  {
    "display_norm": "jakubinski",
    "composite_id": [
      "russland_311_13_17"
    ],
    "family_name": "Jakubinski",
    "given_names": "Lew",
    "name_prefix": null,
    "name_particles": null,
    "name_suffix": null,
    "single_name": null,
    "is_organisation": false,
    "match_found": false,
    "matched_unified_id": null,
    "matched_person_id": null,
    "unified_id": "jakubinski_lew",
    "_source_custom_id": "batch_nopes_016"
  },
  {
    "display_norm": "jamblich",
    "composite_id": [
      "griechenland_69_3_10"
    ],
    "family_name": null,
    "given_names": null,
    "name_prefix": null,
    "name_particles": null,
    "name_suffix": null,
    "single_name": "Jamblich",
    "is_organisation": false,
    "match_found": false,
    "matched_unified_id": null,
    "matched_person_id": null,
    "unified_id": "jamblich",
    "_source_custom_id": "batch_nopes_016"
  },
  {
    "display_norm": "janosch",
    "composite_id": [
      "illustrierte_178_8_14",
      "kinder_37_2_4"
    ],
    "family_name": null,
    "given_names": null,
    "name_prefix": null,
    "name_particles": null,
    "name_suffix": null,
    "single_name": "Janosch",
    "is_organisation": false,
    "match_found": false,
    "matched_unified_id": null,
    "matched_person_id": null,
    "unified_id": "janosch",
    "_source_custom_id": "batch_nopes_016"
  },
  {
    "display_norm": "jansen, elmar",
    "composite_id": [
      "insel_6_1_27"
    ],
    "family_name": "Jansen",
    "given_names": "Elmar",
    "name_prefix": null,
    "name_particles": null,
    "name_suffix": null,
    "single_name": null,
    "is_organisation": false,
    "match_found": false,
    "matched_unified_id": null,
    "matched_person_id": null,
    "unified_id": "jansen_elmar",
    "_source_custom_id": "batch_nopes_016"
  },
  {
    "display_norm": "jansohn, christa",
    "composite_id": [
      "buch_40_2_8"
    ],
    "family_name": "Jansohn",
    "given_names": "Christa",
    "name_prefix": null,
    "name_particles": null,
    "name_suffix": null,
    "single_name": null,
    "is_organisation": false,
    "match_found": false,
    "matched_unified_id": null,
    "matched_person_id": null,
    "unified_id": "jansohn_christa",
    "_source_custom_id": "batch_nopes_016"
  }
]