{
  "nopes_entries": [
    {
      "display_norm": "hauff, hermann",
      "composite_id": [
        "reisen_258_11_13",
        "reisen_185_8_13"
      ],
      "family_name": "Hauff",
      "given_names": "Hermann",
      "name_particles": "",
      "single_name": null,
      "last_norm": "hauff",
      "first_norm": "hermann",
      "single_norm": null,
      "is_organisation": false
    },
    {
      "display_norm": "hauptmann, tatjanna",
      "composite_id": [
        "fremdsprachige_794_32_38"
      ],
      "family_name": "Hauptmann",
      "given_names": "Tatjanna",
      "name_particles": "",
      "single_name": null,
      "last_norm": "hauptmann",
      "first_norm": "tatjanna",
      "single_norm": null,
      "is_organisation": false
    },
    {
      "display_norm": "hausner",
      "composite_id": [
        "kunstbuecher_200_9_38"
      ],
      "family_name": "Hausner",
      "given_names": "Rudolf",
      "name_particles": "",
      "single_name": null,
      "last_norm": "hausner",
      "first_norm": "rudolf",
      "single_norm": null,
      "is_organisation": false
    },
    {
      "display_norm": "hausner, rudolf",
      "composite_id": [
        "kunstbuecher_200_9_38"
      ],
      "family_name": "Hausner",
      "given_names": "Rudolf",
      "name_particles": "",
      "single_name": null,
      "last_norm": "hausner",
      "first_norm": "rudolf",
      "single_norm": null,
      "is_organisation": false
    },
    {
      "display_norm": "haybach, rudolf",
      "composite_id": [
        "illustrierte_161_7_14"
      ],
      "family_name": "HAYBACH",
      "given_names": "Rudolf",
      "name_particles": "",
      "single_name": null,
      "last_norm": "haybach",
      "first_norm": "rudolf",
      "single_norm": null,
      "is_organisation": false
    },
    {
      "display_norm": "haydn",
      "composite_id": [
        "musik_196_8_11"
      ],
      "family_name": null,
      "given_names": null,
      "name_particles": "",
      "single_name": "HAYDN",
      "last_norm": "haydn",
      "first_norm": "",
      "single_norm": "haydn",
      "is_organisation": false
    },
    {
      "display_norm": "hecht, gretel",
      "composite_id": [
        "de-lit-texte_110_5_20",
        "kinder_91_4_4"
      ],
      "family_name": "Hecht",
      "given_names": "Gretel",
      "name_particles": "",
      "single_name": null,
      "last_norm": "hecht",
      "first_norm": "gretel",
      "single_norm": null,
      "is_organisation": false
    },
    {
      "display_norm": "hecht, wolfgang",
      "composite_id": [
        "de-lit-texte_110_5_20",
        "kinder_91_4_4"
      ],
      "family_name": "Hecht",
      "given_names": "Wolfgang",
      "name_particles": "",
      "single_name": null,
      "last_norm": "hecht",
      "first_norm": "wolfgang",
      "single_norm": null,
      "is_organisation": false
    },
    {
      "display_norm": "heckel, martin",
      "composite_id": [
        "deutschland_8_1_4"
      ],
      "family_name": "Heckel",
      "given_names": "Martin",
      "name_particles": "",
      "single_name": null,
      "last_norm": "heckel",
      "first_norm": "martin",
      "single_norm": null,
      "is_organisation": false
    },
    {
      "display_norm": "hecker, karl",
      "composite_id": [
        "kinder_45_2_4"
      ],
      "family_name": "Hecker",
      "given_names": "Karl",
      "name_particles": "",
      "single_name": null,
      "last_norm": "hecker",
      "first_norm": "karl",
      "single_norm": null,
      "is_organisation": false
    },
    {
      "display_norm": "heilmann, joh. dav.",
      "composite_id": [
        "antike_137_6_9"
      ],
      "family_name": "Heilmann",
      "given_names": "Joh. Dav.",
      "name_particles": "",
      "single_name": null,
      "last_norm": "heilmann",
      "first_norm": "joh. dav.",
      "single_norm": null,
      "is_organisation": false
    },
    {
      "display_norm": "heimann-jelinek, felicitas",
      "composite_id": [
        "wien_51_3_10"
      ],
      "family_name": "HEIMANN-JELINEK",
      "given_names": "Felicitas",
      "name_particles": "",
      "single_name": null,
      "last_norm": "heimann-jelinek",
      "first_norm": "felicitas",
      "single_norm": null,
      "is_organisation": false
    },
    {
      "display_norm": "heimatkunde', arbeitsgemeinschaft 'währinger",
      "composite_id": [
        "wien_138_6_10"
      ],
      "family_name": "Heimatkunde'",
      "given_names": "Arbeitsgemeinschaft 'Währinger",
      "name_particles": "",
      "single_name": null,
      "last_norm": "heimatkunde'",
      "first_norm": "arbeitsgemeinschaft 'währinger",
      "single_norm": null,
      "is_organisation": false
    },
    {
      "display_norm": "heine, th. th.",
      "composite_id": [
        "bibliophile_159_7_10"
      ],
      "family_name": "Heine",
      "given_names": "Th. Th.",
      "name_particles": "",
      "single_name": null,
      "last_norm": "heine",
      "first_norm": "th. th.",
      "single_norm": null,
      "is_organisation": false
    },
    {
      "display_norm": "heiss, gernot",
      "composite_id": [
        "oesterreich_101_5_13"
      ],
      "family_name": "Heiss",
      "given_names": "Gernot",
      "name_particles": "",
      "single_name": null,
      "last_norm": "heiss",
      "first_norm": "gernot",
      "single_norm": null,
      "is_organisation": false
    },
    {
      "display_norm": "helm, clementine",
      "composite_id": [
        "kinder_45_2_4"
      ],
      "family_name": "Helm",
      "given_names": "Clementine",
      "name_particles": "",
      "single_name": null,
      "last_norm": "helm",
      "first_norm": "clementine",
      "single_norm": null,
      "is_organisation": false
    },
    {
      "display_norm": "heltau, michael",
      "composite_id": [
        "signierte_179_8_10"
      ],
      "family_name": "Heltau",
      "given_names": "Michael",
      "name_particles": "",
      "single_name": null,
      "last_norm": "heltau",
      "first_norm": "michael",
      "single_norm": null,
      "is_organisation": false
    },
    {
      "display_norm": "hempel, eberhard",
      "composite_id": [
        "oesterreich_189_8_13"
      ],
      "family_name": "Hempel",
      "given_names": "Eberhard",
      "name_particles": "",
      "single_name": null,
      "last_norm": "hempel",
      "first_norm": "eberhard",
      "single_norm": null,
      "is_organisation": false
    },
    {
      "display_norm": "henking, karl h.",
      "composite_id": [
        "kunstbuecher_202_9_38"
      ],
      "family_name": "HENKING",
      "given_names": "Karl H.",
      "name_particles": "",
      "single_name": null,
      "last_norm": "henking",
      "first_norm": "karl h.",
      "single_norm": null,
      "is_organisation": false
    },
    {
      "display_norm": "hensel, s.",
      "composite_id": [
        "musik_51_3_11"
      ],
      "family_name": "HENSEL",
      "given_names": "S.",
      "name_particles": "",
      "single_name": null,
      "last_norm": "hensel",
      "first_norm": "s.",
      "single_norm": null,
      "is_organisation": false
    },
    {
      "display_norm": "hensel, paul",
      "composite_id": [
        "musik_51_3_11"
      ],
      "family_name": "Hensel",
      "given_names": "Paul",
      "name_particles": "",
      "single_name": null,
      "last_norm": "hensel",
      "first_norm": "paul",
      "single_norm": null,
      "is_organisation": false
    },
    {
      "display_norm": "hensel, wilhelm",
      "composite_id": [
        "musik_51_3_11"
      ],
      "family_name": "Hensel",
      "given_names": "Wilhelm",
      "name_particles": "",
      "single_name": null,
      "last_norm": "hensel",
      "first_norm": "wilhelm",
      "single_norm": null,
      "is_organisation": false
    },
    {
      "display_norm": "herget, anton",
      "composite_id": [
        "kinder_40_2_4"
      ],
      "family_name": "Herget",
      "given_names": "Anton",
      "name_particles": "",
      "single_name": null,
      "last_norm": "herget",
      "first_norm": "anton",
      "single_norm": null,
      "is_organisation": false
    },
    {
      "display_norm": "herold, heinrich",
      "composite_id": [
        "kinder_28_2_4"
      ],
      "family_name": "HEROLD",
      "given_names": "Heinrich",
      "name_particles": "",
      "single_name": null,
      "last_norm": "herold",
      "first_norm": "heinrich",
      "single_norm": null,
      "is_organisation": false
    },
    {
      "display_norm": "herrigel, eugen",
      "composite_id": [
        "buddhismus_11_1_3"
      ],
      "family_name": "HERRIGEL",
      "given_names": "Eugen",
      "name_particles": "",
      "single_name": null,
      "last_norm": "herrigel",
      "first_norm": "eugen",
      "single_norm": null,
      "is_organisation": false
    },
    {
      "display_norm": "herwig, malte",
      "composite_id": [
        "de-lit-monographien_106_5_10"
      ],
      "family_name": "HERWIG",
      "given_names": "Malte",
      "name_particles": "",
      "single_name": null,
      "last_norm": "herwig",
      "first_norm": "malte",
      "single_norm": null,
      "is_organisation": false
    },
    {
      "display_norm": "herzen, alexander",
      "composite_id": [
        "russland_83_4_17"
      ],
      "family_name": "Herzen",
      "given_names": "Alexander",
      "name_particles": "",
      "single_name": null,
      "last_norm": "herzen",
      "first_norm": "alexander",
      "single_norm": null,
      "is_organisation": false
    },
    {
      "display_norm": "herzog, elizabeth",
      "composite_id": [
        "judentum_186_8_9"
      ],
      "family_name": "HERZOG",
      "given_names": "Elizabeth",
      "name_particles": "",
      "single_name": null,
      "last_norm": "herzog",
      "first_norm": "elizabeth",
      "single_norm": null,
      "is_organisation": false
    },
    {
      "display_norm": "hesse, bruno",
      "composite_id": [
        "kunstbuecher_204_9_38"
      ],
      "family_name": "Hesse",
      "given_names": "Bruno",
      "name_particles": "",
      "single_name": null,
      "last_norm": "hesse",
      "first_norm": "bruno",
      "single_norm": null,
      "is_organisation": false
    },
    {
      "display_norm": "heuer, wolfgang",
      "composite_id": [
        "bibliophile_126_6_10"
      ],
      "family_name": "Heuer",
      "given_names": "Wolfgang",
      "name_particles": "",
      "single_name": null,
      "last_norm": "heuer",
      "first_norm": "wolfgang",
      "single_norm": null,
      "is_organisation": false
    }
  ],
  "existing_people_context": [
    {
      "person_id": 2642,
      "unified_id": "hauff_l_a",
      "family_name": "Hauff",
      "given_names": "L. A.",
      "name_particles": null,
      "single_name": null,
      "is_organisation": false
    },
    {
      "person_id": 2643,
      "unified_id": "hauff_wilhelm",
      "family_name": "Hauff",
      "given_names": "Wilhelm",
      "name_particles": null,
      "single_name": null,
      "is_organisation": false
    },
    {
      "person_id": 2689,
      "unified_id": "hecht_werner",
      "family_name": "Hecht",
      "given_names": "Werner",
      "name_particles": null,
      "single_name": null,
      "is_organisation": false
    },
    {
      "person_id": 2648,
      "unified_id": "hauptmann_carl",
      "family_name": "Hauptmann",
      "given_names": "Carl",
      "name_particles": null,
      "single_name": null,
      "is_organisation": false
    },
    {
      "person_id": 2649,
      "unified_id": "hauptmann_elisabeth",
      "family_name": "Hauptmann",
      "given_names": "Elisabeth",
      "name_particles": null,
      "single_name": null,
      "is_organisation": false
    },
    {
      "person_id": 2650,
      "unified_id": "hauptmann_gerhard",
      "family_name": "Hauptmann",
      "given_names": "Gerhard",
      "name_particles": null,
      "single_name": null,
      "is_organisation": false
    },
    {
      "person_id": 2651,
      "unified_id": "hauptmann_gerhart",
      "family_name": "Hauptmann",
      "given_names": "Gerhart",
      "name_particles": null,
      "single_name": null,
      "is_organisation": false
    },
    {
      "person_id": 2719,
      "unified_id": "heine_alexander",
      "family_name": "Heine",
      "given_names": "Alexander",
      "name_particles": null,
      "single_name": null,
      "is_organisation": false
    },
    {
      "person_id": 2720,
      "unified_id": "heine_heinrich",
      "family_name": "Heine",
      "given_names": "Heinrich",
      "name_particles": null,
      "single_name": null,
      "is_organisation": false
    },
    {
      "person_id": 2721,
      "unified_id": "heine_th_th",
      "family_name": "Heine",
      "given_names": "Th.Th.",
      "name_particles": null,
      "single_name": null,
      "is_organisation": false
    },
    {
      "person_id": 2764,
      "unified_id": "hempel_rose",
      "family_name": "Hempel",
      "given_names": "Rose",
      "name_particles": null,
      "single_name": null,
      "is_organisation": false
    },
    {
      "person_id": 2829,
      "unified_id": "herzog_andreas",
      "family_name": "Herzog",
      "given_names": "Andreas",
      "name_particles": null,
      "single_name": null,
      "is_organisation": false
    },
    {
      "person_id": 2830,
      "unified_id": "herzog_sigrid",
      "family_name": "Herzog",
      "given_names": "Sigrid",
      "name_particles": null,
      "single_name": null,
      "is_organisation": false
    },
    {
      "person_id": 2831,
      "unified_id": "herzog_urs",
      "family_name": "Herzog",
      "given_names": "Urs",
      "name_particles": null,
      "single_name": null,
      "is_organisation": false
    },
    {
      "person_id": 2833,
      "unified_id": "herzog_wilhelm",
      "family_name": "Herzog",
      "given_names": "Wilhelm",
      "name_particles": null,
      "single_name": null,
      "is_organisation": false
    },
    {
      "person_id": 2680,
      "unified_id": "haydn_joseph",
      "family_name": "Haydn",
      "given_names": "Joseph",
      "name_particles": null,
      "single_name": null,
      "is_organisation": false
    },
    {
      "person_id": 2838,
      "unified_id": "hesse_eva",
      "family_name": "Hesse",
      "given_names": "Eva",
      "name_particles": null,
      "single_name": null,
      "is_organisation": false
    },
    {
      "person_id": 2839,
      "unified_id": "hesse_heiner",
      "family_name": "Hesse",
      "given_names": "Heiner",
      "name_particles": null,
      "single_name": null,
      "is_organisation": false
    },
    {
      "person_id": 2840,
      "unified_id": "hesse_hermann",
      "family_name": "Hesse",
      "given_names": "Hermann",
      "name_particles": null,
      "single_name": null,
      "is_organisation": false
    },
    {
      "person_id": 2841,
      "unified_id": "hesse_isa",
      "family_name": "Hesse",
      "given_names": "Isa",
      "name_particles": null,
      "single_name": null,
      "is_organisation": false
    },
    {
      "person_id": 2842,
      "unified_id": "hesse_marie",
      "family_name": "Hesse",
      "given_names": "Marie",
      "name_particles": null,
      "single_name": null,
      "is_organisation": false
    },
    {
      "person_id": 2843,
      "unified_id": "hesse_martin",
      "family_name": "Hesse",
      "given_names": "Martin",
      "name_particles": null,
      "single_name": null,
      "is_organisation": false
    },
    {
      "person_id": 2844,
      "unified_id": "hesse_ninon",
      "family_name": "Hesse",
      "given_names": "Ninon",
      "name_particles": null,
      "single_name": null,
      "is_organisation": false
    },
    {
      "person_id": 2691,
      "unified_id": "heckel_erich",
      "family_name": "Heckel",
      "given_names": "Erich",
      "name_particles": null,
      "single_name": null,
      "is_organisation": false
    },
    {
      "person_id": 2755,
      "unified_id": "helm_michael",
      "family_name": "Helm",
      "given_names": "Michael",
      "name_particles": null,
      "single_name": null,
      "is_organisation": false
    },
    {
      "person_id": 2756,
      "unified_id": "helm_rudolf",
      "family_name": "Helm",
      "given_names": "Rudolf",
      "name_particles": null,
      "single_name": null,
      "is_organisation": false
    },
    {
      "person_id": 2666,
      "unified_id": "hausner_ernst",
      "family_name": "Hausner",
      "given_names": "Ernst",
      "name_particles": null,
      "single_name": null,
      "is_organisation": false
    }
  ]
}